MANIFEST.in
setup.py
QEnvPython311.egg-info/PKG-INFO
QEnvPython311.egg-info/SOURCES.txt
QEnvPython311.egg-info/dependency_links.txt
QEnvPython311.egg-info/top_level.txt
QPT_SDK/__init__.py
QPT_SDK/QEnvPython/__init__.py
QPT_SDK/QEnvPython/python311/LICENSE.txt
QPT_SDK/QEnvPython/python311/_asyncio.pyd
QPT_SDK/QEnvPython/python311/_bz2.pyd
QPT_SDK/QEnvPython/python311/_ctypes.pyd
QPT_SDK/QEnvPython/python311/_decimal.pyd
QPT_SDK/QEnvPython/python311/_elementtree.pyd
QPT_SDK/QEnvPython/python311/_hashlib.pyd
QPT_SDK/QEnvPython/python311/_lzma.pyd
QPT_SDK/QEnvPython/python311/_msi.pyd
QPT_SDK/QEnvPython/python311/_multiprocessing.pyd
QPT_SDK/QEnvPython/python311/_overlapped.pyd
QPT_SDK/QEnvPython/python311/_queue.pyd
QPT_SDK/QEnvPython/python311/_socket.pyd
QPT_SDK/QEnvPython/python311/_sqlite3.pyd
QPT_SDK/QEnvPython/python311/_ssl.pyd
QPT_SDK/QEnvPython/python311/_uuid.pyd
QPT_SDK/QEnvPython/python311/_zoneinfo.pyd
QPT_SDK/QEnvPython/python311/libcrypto-3.dll
QPT_SDK/QEnvPython/python311/libffi-8.dll
QPT_SDK/QEnvPython/python311/libssl-3.dll
QPT_SDK/QEnvPython/python311/pyexpat.pyd
QPT_SDK/QEnvPython/python311/python.cat
QPT_SDK/QEnvPython/python311/python.exe
QPT_SDK/QEnvPython/python311/python3.dll
QPT_SDK/QEnvPython/python311/python311._pth
QPT_SDK/QEnvPython/python311/python311.dll
QPT_SDK/QEnvPython/python311/python311.zip
QPT_SDK/QEnvPython/python311/pythonw.exe
QPT_SDK/QEnvPython/python311/select.pyd
QPT_SDK/QEnvPython/python311/sqlite3.dll
QPT_SDK/QEnvPython/python311/unicodedata.pyd
QPT_SDK/QEnvPython/python311/vcruntime140.dll
QPT_SDK/QEnvPython/python311/vcruntime140_1.dll
QPT_SDK/QEnvPython/python311/winsound.pyd
QPT_SDK/QEnvPython/python311/Lib/site-packages/distutils-precedence.pth
QPT_SDK/QEnvPython/python311/Lib/site-packages/_distutils_hack/__init__.py
QPT_SDK/QEnvPython/python311/Lib/site-packages/_distutils_hack/override.py
QPT_SDK/QEnvPython/python311/Lib/site-packages/pip/__init__.py
QPT_SDK/QEnvPython/python311/Lib/site-packages/pip/__main__.py
QPT_SDK/QEnvPython/python311/Lib/site-packages/pip/__pip-runner__.py
QPT_SDK/QEnvPython/python311/Lib/site-packages/pip/py.typed
QPT_SDK/QEnvPython/python311/Lib/site-packages/pip-23.3.1.dist-info/AUTHORS.txt
QPT_SDK/QEnvPython/python311/Lib/site-packages/pip-23.3.1.dist-info/INSTALLER
QPT_SDK/QEnvPython/python311/Lib/site-packages/pip-23.3.1.dist-info/LICENSE.txt
QPT_SDK/QEnvPython/python311/Lib/site-packages/pip-23.3.1.dist-info/METADATA
QPT_SDK/QEnvPython/python311/Lib/site-packages/pip-23.3.1.dist-info/RECORD
QPT_SDK/QEnvPython/python311/Lib/site-packages/pip-23.3.1.dist-info/REQUESTED
QPT_SDK/QEnvPython/python311/Lib/site-packages/pip-23.3.1.dist-info/WHEEL
QPT_SDK/QEnvPython/python311/Lib/site-packages/pip-23.3.1.dist-info/entry_points.txt
QPT_SDK/QEnvPython/python311/Lib/site-packages/pip-23.3.1.dist-info/top_level.txt
QPT_SDK/QEnvPython/python311/Lib/site-packages/setuptools-68.2.2.dist-info/INSTALLER
QPT_SDK/QEnvPython/python311/Lib/site-packages/setuptools-68.2.2.dist-info/LICENSE
QPT_SDK/QEnvPython/python311/Lib/site-packages/setuptools-68.2.2.dist-info/METADATA
QPT_SDK/QEnvPython/python311/Lib/site-packages/setuptools-68.2.2.dist-info/RECORD
QPT_SDK/QEnvPython/python311/Lib/site-packages/setuptools-68.2.2.dist-info/REQUESTED
QPT_SDK/QEnvPython/python311/Lib/site-packages/setuptools-68.2.2.dist-info/WHEEL
QPT_SDK/QEnvPython/python311/Lib/site-packages/setuptools-68.2.2.dist-info/entry_points.txt
QPT_SDK/QEnvPython/python311/Lib/site-packages/setuptools-68.2.2.dist-info/top_level.txt
QPT_SDK/QEnvPython/python311/Lib/site-packages/wheel-0.41.3.dist-info/INSTALLER
QPT_SDK/QEnvPython/python311/Lib/site-packages/wheel-0.41.3.dist-info/LICENSE.txt
QPT_SDK/QEnvPython/python311/Lib/site-packages/wheel-0.41.3.dist-info/METADATA
QPT_SDK/QEnvPython/python311/Lib/site-packages/wheel-0.41.3.dist-info/RECORD
QPT_SDK/QEnvPython/python311/Lib/site-packages/wheel-0.41.3.dist-info/REQUESTED
QPT_SDK/QEnvPython/python311/Lib/site-packages/wheel-0.41.3.dist-info/WHEEL
QPT_SDK/QEnvPython/python311/Lib/site-packages/wheel-0.41.3.dist-info/entry_points.txt
