Metadata-Version: 2.1
Name: QEnvPython311
Version: 3.11.6
Summary: QPT-Python环境打包工具 Python SDK
Home-page: https://github.com/GT-ZhangAcer/QPT
Author: GT-ZhangAcer
Author-email: zhangacer@foxmail.com
License: MIT
